[
  {
    "providerName": "random",
    "url": "https://raw.githubusercontent.com/pulumi/pulumi-random/v4.16.4/provider/cmd/pulumi-resource-random/schema.json",
    "kotlinVersion": "4.16.4.0-SNAPSHOT",
    "javaVersion": "4.16.4",
    "javaGitTag": "v4.16.4",
    "customDependencies": [
    ]
  },
  {
    "providerName": "azure",
    "url": "https://gist.githubusercontent.com/jplewa/3a13cf2ed18aa39de8cb9189dd487356/raw/6aa6c7929106aad8661478080eafb45e5cf03e8f/schema-azure-v5.87.0-subset-for-build.json",
    "kotlinVersion": "5.87.0.0-SNAPSHOT",
    "javaVersion": "5.87.0",
    "javaGitTag": "v5.87.0",
    "customDependencies": [
    ]
  },
  {
    "providerName": "azure-native",
    "url": "https://gist.githubusercontent.com/jplewa/cea43edd61c3284b29c037cd094e0e77/raw/f32ad6c02c8b90efcea1ae10a84a2d92951bab17/schema-azure-native-v1.103.0-subset-for-build.json",
    "kotlinVersion": "1.103.0.0-SNAPSHOT",
    "javaVersion": "1.103.0",
    "javaGitTag": "v1.103.0",
    "customDependencies": [
    ]
  },
  {
    "providerName": "gcp",
    "url": "https://gist.githubusercontent.com/jplewa/0988583befa715aedcde660feae81002/raw/4cc4ace69b244a3c552071f90e7662e5abb7e91e/schema-gcp-v6.59.0-subset-for-build.json",
    "kotlinVersion": "6.59.0.0-SNAPSHOT",
    "javaVersion": "6.59.0",
    "javaGitTag": "v6.59.0",
    "customDependencies": [
    ]
  },
  {
    "providerName": "google-native",
    "url": "https://gist.githubusercontent.com/jplewa/544b1de415bca905cee9f135c119089e/raw/5b29ca08103a0c00dccfcacb834637853bc56241/schema-google-native-v0.31.0-subset-for-build.json",
    "kotlinVersion": "0.31.0.0-SNAPSHOT",
    "javaVersion": "0.31.0",
    "javaGitTag": "v0.31.0",
    "customDependencies": [
    ]
  },
  {
    "providerName": "kubernetes",
    "url": "https://gist.githubusercontent.com/jplewa/1d396426206698b29a884b5d85391ee3/raw/cfc2220d07524c9f99e5be14928f91819323ea80/schema-kubernetes-v3.30.1-subset-for-build.json",
    "kotlinVersion": "3.30.1.0-SNAPSHOT",
    "javaVersion": "3.30.1",
    "javaGitTag": "v3.30.1",
    "customDependencies": [
    ]
  }
]
