[
  {
    "providerName": "cloudflare",
    "url": "https://raw.githubusercontent.com/pulumi/pulumi-cloudflare/v4.12.1/provider/cmd/pulumi-resource-cloudflare/schema.json",
    "kotlinVersion": "4.12.1.0-SNAPSHOT",
    "javaVersion": "4.12.1",
    "javaGitTag": "v4.12.1",
    "customDependencies": [
      "com.pulumi:cloudflare:4.12.1"
    ]
  },
  {
    "providerName": "slack",
    "url": "https://raw.githubusercontent.com/pulumi/pulumi-slack/v0.3.0/provider/cmd/pulumi-resource-slack/schema.json",
    "kotlinVersion": "0.3.0.0-SNAPSHOT",
    "javaVersion": "0.3.0",
    "javaGitTag": "v0.3.0",
    "customDependencies": [
      "com.pulumi:slack:0.3.0",
      "org.jetbrains.kotlinx:kotlinx-serialization-json-jvm:1.4.1"
    ]
  },
  {
    "providerName": "github",
    "url": "https://raw.githubusercontent.com/pulumi/pulumi-github/v4.17.0/provider/cmd/pulumi-resource-github/schema.json",
    "kotlinVersion": "4.17.0.0-SNAPSHOT",
    "javaVersion": "4.17.0",
    "javaGitTag": "v4.17.0",
    "customDependencies": [
      "com.pulumi:github:4.17.0",
      "org.jetbrains.kotlinx:kotlinx-serialization-json-jvm:1.4.1"
    ]
  },
  {
    "providerName": "random",
    "url": "https://raw.githubusercontent.com/pulumi/pulumi-random/v4.6.0/provider/cmd/pulumi-resource-random/schema.json",
    "kotlinVersion": "4.6.0.0-SNAPSHOT",
    "javaVersion": "4.6.0",
    "javaGitTag": "v4.6.0",
    "customDependencies": [
      "com.pulumi:random:4.6.0",
      "org.jetbrains.kotlinx:kotlinx-serialization-json-jvm:1.4.1"
    ]
  },
  {
    "providerName": "gcp",
    "url": "https://gist.githubusercontent.com/jplewa/eaae32a6742a8ae4e0dd66af4c1dd56b/raw/040975f09052390ba756b841856248708bb2cdd6/schema-gcp-classic-v6.39.0-subset-for-build.json",
    "kotlinVersion": "6.39.0.0-SNAPSHOT",
    "javaVersion": "6.39.0",
    "javaGitTag": "v6.39.0",
    "customDependencies": [
      "com.pulumi:gcp:6.39.0",
      "org.jetbrains.kotlinx:kotlinx-serialization-json-jvm:1.4.1"
    ]
  },
  {
    "providerName": "google-native",
    "url": "https://gist.githubusercontent.com/jplewa/73836b04be29884b0b02872843f9136a/raw/ee064931b6cae0bdb3c7ac0adf83e1c019c5fa79/schema-google-native-v0.27.0-subset-for-build.json",
    "kotlinVersion": "0.27.0.0-SNAPSHOT",
    "javaVersion": "0.27.0",
    "javaGitTag": "v0.27.0",
    "customDependencies": [
      "com.pulumi:google-native:0.27.0"
    ]
  },
  {
    "providerName": "aws",
    "url": "https://gist.githubusercontent.com/jplewa/ab012d882e1facf10c196e85920878bc/raw/9c6bf001603c27907276f9b8d11190cc0646063e/schema-aws-classic-v5.16.2-subset-for-build.json",
    "kotlinVersion": "5.16.2.0-SNAPSHOT",
    "javaVersion": "5.16.2",
    "javaGitTag": "v5.16.2",
    "customDependencies": [
      "com.pulumi:aws:5.16.2",
      "org.jetbrains.kotlinx:kotlinx-serialization-json-jvm:1.4.1"
    ]
  },
  {
    "providerName": "kubernetes",
    "url": "https://raw.githubusercontent.com/pulumi/pulumi-kubernetes/v3.22.1/provider/cmd/pulumi-resource-kubernetes/schema.json",
    "kotlinVersion": "3.22.1.0-SNAPSHOT",
    "javaVersion": "3.22.1",
    "javaGitTag": "v3.22.1",
    "customDependencies": [
      "com.pulumi:kubernetes:3.22.1",
      "org.jetbrains.kotlinx:kotlinx-serialization-json-jvm:1.4.1"
    ]
  }
]
